fileindex/__init__.py
fileindex/__main__.py
fileindex/main.py
fileindex/py.typed
fileindex/cli/__init__.py
fileindex/cli/style.py
fileindex/cli/welcome.py
fileindex/core/cache.py
fileindex/core/scan.py
fileindex/core/search.py
fileindex-0.1.0.dist-info/licenses/LICENSE
fileindex-0.1.0.dist-info/METADATA
fileindex-0.1.0.dist-info/WHEEL
fileindex-0.1.0.dist-info/entry_points.txt
fileindex-0.1.0.dist-info/top_level.txt
fileindex-0.1.0.dist-info/RECORD
