Metadata-Version: 2.4
Name: fileindex
Version: 0.1.0
Summary: Fast local file indexing and search tool with smart caching and duplicate detection
Author-email: Dhritikrishna Tripathi <dhritikrishnat@gmail.com>
Maintainer-email: Dhritikrishna Tripathi <dhritikrishnat@gmail.com>
License-Expression: MIT
Project-URL: Homepage, https://github.com/Dhritikrishna123/file-index
Project-URL: Documentation, https://github.com/Dhritikrishna123/file-index#readme
Project-URL: Repository, https://github.com/Dhritikrishna123/file-index.git
Project-URL: Bug Tracker, https://github.com/Dhritikrishna123/file-index/issues
Project-URL: Changelog, https://github.com/Dhritikrishna123/file-index/releases
Keywords: file,search,index,cli,duplicate,indexing,local-search
Classifier: Development Status :: 4 - Beta
Classifier: Environment :: Console
Classifier: Intended Audience :: Developers
Classifier: Intended Audience :: End Users/Desktop
Classifier: Intended Audience :: System Administrators
Classifier: Natural Language :: English
Classifier: Operating System :: OS Independent
Classifier: Operating System :: Microsoft :: Windows
Classifier: Operating System :: POSIX :: Linux
Classifier: Operating System :: MacOS
Classifier: Programming Language :: Python
Classifier: Programming Language :: Python :: 3
Classifier: Programming Language :: Python :: 3.8
Classifier: Programming Language :: Python :: 3.9
Classifier: Programming Language :: Python :: 3.10
Classifier: Programming Language :: Python :: 3.11
Classifier: Programming Language :: Python :: 3.12
Classifier: Programming Language :: Python :: 3.13
Classifier: Programming Language :: Python :: 3.14
Classifier: Topic :: System :: Archiving
Classifier: Topic :: Utilities
Classifier: Typing :: Typed
Requires-Python: >=3.8
License-File: LICENSE
Provides-Extra: dev
Requires-Dist: pytest>=7.0; extra == "dev"
Requires-Dist: pytest-cov>=4.0; extra == "dev"
Provides-Extra: test
Requires-Dist: pytest>=7.0; extra == "test"
Requires-Dist: pytest-cov>=4.0; extra == "test"
Dynamic: license-file
